gib_lang/__init__.py
gib_lang/__main__.py
gib_lang/cli.py
gib_lang/exceptions.py
gib_lang/instruction.py
gib_lang/machine.py
gib_lang/py.typed
gib_lang/runner.py
gib_lang/tape.py
gib_lang-0.2.2.dist-info/entry_points.txt
gib_lang-0.2.2.dist-info/licenses/LICENSE
gib_lang-0.2.2.dist-info/WHEEL
gib_lang-0.2.2.dist-info/METADATA
gib_lang-0.2.2.dist-info/RECORD
