Metadata-Version: 2.4
Name: gib-lang
Version: 0.2.2
Summary: Gibberish Language (gib-lang) interpreter
Keywords: esolang,turing machine,interpreter,gibberish
Author: Alifa Izzan Akhsani
Requires-Python: >=3.10
Classifier: Programming Language :: Python :: 3
Classifier: License :: OSI Approved :: MIT License
Classifier: Operating System :: OS Independent
Classifier: Topic :: Software Development :: Interpreters
Classifier: Topic :: Software Development :: Libraries :: Python Modules
License-File: LICENSE
Project-URL: Home, https://github.com/symefa/gib-lang
